setup.py
jargon/__init__.py
jargon.egg-info/PKG-INFO
jargon.egg-info/SOURCES.txt
jargon.egg-info/dependency_links.txt
jargon.egg-info/namespace_packages.txt
jargon.egg-info/not-zip-safe
jargon.egg-info/top_level.txt