Metadata-Version: 1.0
Name: jargon
Version: 0.1
Summary: jargon
Home-page: UNKNOWN
Author: Jargon
Author-email: info@jargon.io
License: UNKNOWN
Platform: UNKNOWN
